setup.cfg
setup.py
rack_iam/__init__.py
rack_iam.egg-info/PKG-INFO
rack_iam.egg-info/SOURCES.txt
rack_iam.egg-info/dependency_links.txt
rack_iam.egg-info/requires.txt
rack_iam.egg-info/top_level.txt
rack_iam/core/__init__.py
rack_iam/core/group.py
rack_iam/core/helpers.py
rack_iam/core/policy.py
rack_iam/core/role.py
rack_iam/core/statement.py
rack_iam/core/user.py
rack_iam/transform/__init__.py
rack_iam/transform/cfdict/__init__.py
rack_iam/transform/cfdict/group.py
rack_iam/transform/cfdict/policy.py
rack_iam/transform/cfdict/role.py
rack_iam/transform/cfdict/statement.py
rack_iam/transform/cfdict/user.py